starknet_pathfinder_crypto-0.1.0.dist-info/METADATA
starknet_pathfinder_crypto-0.1.0.dist-info/WHEEL
starknet_pathfinder_crypto/__init__.py
starknet_pathfinder_crypto/starknet_pathfinder_crypto.cpython-39-x86_64-linux-gnu.so
starknet_pathfinder_crypto-0.1.0.dist-info/RECORD
