Metadata-Version: 2.1
Name: starknet_pathfinder_crypto
Version: 0.1.0
Classifier: Programming Language :: Rust
Classifier: Programming Language :: Python :: Implementation :: CPython
Classifier: Programming Language :: Python :: Implementation :: PyPy
License: MIT or Apache-2.0
Requires-Python: >=3.8
